{"meta": {"timestamp": 1753866343}, "payload": [{"id": 1, "dsp": "JHAL", "vin": "WF0EXXTTRERG14453", "reg": "WV74OPE"}, {"id": 2, "dsp": "RXTP", "vin": "WF0YXXTTGYNB28040", "reg": "MT72VEO"}, {"id": 3, "dsp": "UKED", "vin": "VXEVJHYV9R7867810", "reg": "VN74LRO"}, {"id": 4, "dsp": "JHAL", "vin": "WF0YXXTTGYJT73935", "reg": "MJ68LFZ"}, {"id": 5, "dsp": "LIGE", "vin": "VXEVLEHT0R7859585", "reg": "DW74NDJ"}, {"id": 6, "dsp": "ALMD", "vin": "W1V9106332P349251", "reg": "KO21OCD"}, {"id": 7, "dsp": "ARRI", "vin": "WF0EXXTTREMR02562", "reg": "LG71OEW"}, {"id": 8, "dsp": "UKED", "vin": "VXEVJYHV0R7853892", "reg": "VK74MPF"}, {"id": 9, "dsp": "RXTP", "vin": "YARVBBHXHGZ123661", "reg": "MJ18RXV"}, {"id": 10, "dsp": "JHAL", "vin": "VF7YB2MFA12E15209", "reg": "ND17TFO"}, {"id": 11, "dsp": "JHAL", "vin": "WV1ZZZ7H5RX048049", "reg": "GJ74OUA"}, {"id": 12, "dsp": "ARRI", "vin": "W1V3HBFZ1SP713399", "reg": "KW24TWM"}, {"id": 13, "dsp": "LIGE", "vin": "WF0EXXTTREMP73049", "reg": "LC21YSX"}, {"id": 14, "dsp": "LIGE", "vin": "VXEVLEHT0R7859571", "reg": "DW74NBF"}, {"id": 15, "dsp": "JHAL", "vin": "WF0YXXTTGYJT70784", "reg": "BG68PKY"}, {"id": 16, "dsp": "LIGE", "vin": "VXEVLEHT1R7859076", "reg": "DW74NHM"}, {"id": 17, "dsp": "RXTP", "vin": "VF3VBBHVBJZ063905", "reg": "NV18UNJ"}, {"id": 18, "dsp": "ALMD", "vin": "W1V9106332P349254", "reg": "KO21OCH"}, {"id": 19, "dsp": "RXTP", "vin": "WF0YXXTTGYNB28030", "reg": "MT72VDR"}, {"id": 20, "dsp": "LIGE", "vin": "W1V9106332P364058", "reg": "KO21TFF"}, {"id": 21, "dsp": "LIGE", "vin": "VXEVLEHT9R7859570", "reg": "DW74NHA"}, {"id": 22, "dsp": "ARRI", "vin": "WF0EXXTTRERR77615", "reg": "WP24NTK"}, {"id": 23, "dsp": "LIGE", "vin": "W1V3UBFZ8SP789374", "reg": "KW74TKX"}, {"id": 24, "dsp": "ARRI", "vin": "W1V3HBFZ7SP719224", "reg": "KW24GNU"}, {"id": 25, "dsp": "ARRI", "vin": "WF0EXXTTREMR01395", "reg": "LG71OFH"}, {"id": 26, "dsp": "RXTP", "vin": "W1V9016332P335274", "reg": "KW21WMM"}, {"id": 27, "dsp": "ARRI", "vin": "VXEVBYHVMRZ003685", "reg": "DP73UES"}, {"id": 28, "dsp": "LIGE", "vin": "W1V9106332P264839", "reg": "KW20KBE"}, {"id": 29, "dsp": "RXTP", "vin": "WF0YXXTTGYPD84465", "reg": "ML73ZKW"}, {"id": 30, "dsp": "LIGE", "vin": "W1V9106332P348785", "reg": "KS21OMC"}, {"id": 31, "dsp": "UKED", "vin": "VXEUBYHRMP7852399", "reg": "VN73AWX"}, {"id": 32, "dsp": "RXTP", "vin": "WF0YXXTTGYLB77154", "reg": "SL70JYN"}, {"id": 33, "dsp": "JHAL", "vin": "WF0YXXTTGYJT74047", "reg": "MJ68LFW"}, {"id": 34, "dsp": "RXTP", "vin": "WDB9076352P060966", "reg": "LO68HRN"}, {"id": 35, "dsp": "UKED", "vin": "VXEVJYHV2R7853182", "reg": "VK74MLF"}, {"id": 36, "dsp": "JHAL", "vin": "WDB9106332P118121", "reg": "YH20UGM"}, {"id": 37, "dsp": "RXTP", "vin": "WF0YXXTTGYPD84370", "reg": "MW23GKX"}, {"id": 38, "dsp": "RXTP", "vin": "W0L3F7012FV604682", "reg": "VU69VKL"}, {"id": 39, "dsp": "UKED", "vin": "YARVLEHTMRZ055311", "reg": "BD74VJF"}, {"id": 40, "dsp": "UKED", "vin": "VXEVJYHV7R7869071", "reg": "VN74SBY"}, {"id": 41, "dsp": "LIGE", "vin": "W1V9106332P348798", "reg": "KS21OLR"}, {"id": 42, "dsp": "RXTP", "vin": "WF0YXXTTGYNB28541", "reg": "MT72VFA"}, {"id": 43, "dsp": "UKED", "vin": "VXEYDBPFCPG047695", "reg": "VK24DOA"}, {"id": 44, "dsp": "ARRI", "vin": "WF0EXXTTREPM26657", "reg": "WP24NXU"}, {"id": 45, "dsp": "UKED", "vin": "VXEVJYHV1R7852993", "reg": "VK74LHO"}, {"id": 46, "dsp": "JHAL", "vin": "VXEVBYHRMP7867009", "reg": "DN73BFA"}, {"id": 47, "dsp": "RXTP", "vin": "WF0YXXTTGYPD84446", "reg": "ML73ZKY"}, {"id": 48, "dsp": "JHAL", "vin": "WV1ZZZ7HZGH138493", "reg": "DF16XGL"}, {"id": 49, "dsp": "UKED", "vin": "VXEVJYHV8R7868091", "reg": "VN74LRA"}, {"id": 50, "dsp": "RXTP", "vin": "VF3XS9HUCBZ007571", "reg": "RK11OXL"}, {"id": 51, "dsp": "RXTP", "vin": "YARVLEHTMRZ044423", "reg": "PN74OJC"}, {"id": 52, "dsp": "RXTP", "vin": "WF0YXXTTGYNB28045", "reg": "MT72VDP"}, {"id": 53, "dsp": "UKED", "vin": "VXEVBYHRMP7867261", "reg": "VN73BDE"}, {"id": 54, "dsp": "ALMD", "vin": "WF0EXXTTREMA09976", "reg": "LG71OXZ"}, {"id": 55, "dsp": "JHAL", "vin": "VXEVJYHV2R7841873", "reg": "DT24MFF"}, {"id": 56, "dsp": "JHAL", "vin": "WDB9066332S696666", "reg": "YJ63OAZ"}, {"id": 57, "dsp": "UKED", "vin": "VXEVJYHV4R7853197", "reg": "VK74MMV"}, {"id": 58, "dsp": "UKED", "vin": "VXEVBYHRMP7852422", "reg": "KS73FFB"}, {"id": 59, "dsp": "JHAL", "vin": "VXEVBYHRKM7802423", "reg": "DS70LVK"}, {"id": 60, "dsp": "UKED", "vin": "VXEVJYHV5R7853192", "reg": "VK74MGY"}, {"id": 61, "dsp": "ALMD", "vin": "WF0EXXTTREMA11346", "reg": "LG71PWK"}, {"id": 62, "dsp": "ALMD", "vin": "W1V9106332P362530", "reg": "KO21DZD"}, {"id": 63, "dsp": "LIGE", "vin": "VF3VJYHVMR7808056", "reg": "MM24GVY"}, {"id": 64, "dsp": "LIGE", "vin": "VXEVBYHRMP7852313", "reg": "DY73OJS"}, {"id": 65, "dsp": "RXTP", "vin": "WF0YXXTTGYJJ21975", "reg": "CV68BYW"}, {"id": 66, "dsp": "RXTP", "vin": "W0LF7AHA6BV618663", "reg": "YE60FXA"}, {"id": 67, "dsp": "ALMD", "vin": "W1V9106332P349263", "reg": "KO21ODT"}, {"id": 68, "dsp": "RXTP", "vin": "YARVLEHTMRZ046409", "reg": "PN74OJK"}, {"id": 69, "dsp": "ARRI", "vin": "WF0EXXTTREMP72975", "reg": "LC21YMO"}, {"id": 70, "dsp": "UKED", "vin": "VXEVJYHV0R7868084", "reg": "VN74LUP"}, {"id": 71, "dsp": "RXTP", "vin": "VXEVBYHRKLZ004234", "reg": "VU69VKL"}, {"id": 72, "dsp": "ARRI", "vin": "VF3VBYHRMP7803470", "reg": "RA72HSC"}, {"id": 73, "dsp": "ALMD", "vin": "W1V9106332P348423", "reg": "KT21XBU"}, {"id": 74, "dsp": "UKED", "vin": "VXEYDBPFCPG057473", "reg": "DL73SXO"}, {"id": 75, "dsp": "RXTP", "vin": "VF7VFAHKHKZ038625", "reg": "YE19VMO"}, {"id": 76, "dsp": "ARRI", "vin": "VF7VBYHRMR7811667", "reg": "MT24UPD"}, {"id": 77, "dsp": "ARRI", "vin": "WF0EXXTTREMA13604", "reg": "LD71DVR"}, {"id": 78, "dsp": "ALMD", "vin": "W1V9106332P272868", "reg": "KN70KCG"}, {"id": 79, "dsp": "RXTP", "vin": "WF0YXXTTGYJG18937", "reg": "CV69KFP"}, {"id": 80, "dsp": "JHAL", "vin": "VF1FL000X73415688", "reg": "MA74NHG"}, {"id": 81, "dsp": "LIGE", "vin": "W1V9106332P364066", "reg": "KO21SHJ"}, {"id": 82, "dsp": "JHAL", "vin": "W0LMRFESCFB077382", "reg": "YH15ULX"}, {"id": 83, "dsp": "RXTP", "vin": "WF0EXXTTRELE17330", "reg": "BN70YED"}, {"id": 84, "dsp": "JHAL", "vin": "VF1FL000071458884", "reg": "FM23UEF"}, {"id": 85, "dsp": "JHAL", "vin": "WF0YXXTTGYJR40518", "reg": "LX68GXF"}, {"id": 86, "dsp": "UKED", "vin": "W1V9076352P364196", "reg": "BJ71MXG"}, {"id": 87, "dsp": "RXTP", "vin": "WF0YXXTTGYNS60345", "reg": "MW22MUB"}, {"id": 88, "dsp": "RXTP", "vin": "YARVLEHTMRZ046399", "reg": "PN74OJJ"}, {"id": 89, "dsp": "ALMD", "vin": "W1V9106332P348797", "reg": "KT21XBJ"}, {"id": 90, "dsp": "RXTP", "vin": "VXEVBYHRMN7014247", "reg": "AV22KSY"}, {"id": 91, "dsp": "RXTP", "vin": "WDF44760323562145", "reg": "KM19EGV"}, {"id": 92, "dsp": "ALMD", "vin": "WF0EXXTTREMG58544", "reg": "LD71YFL"}, {"id": 93, "dsp": "LIGE", "vin": "VXEVBYHRMN7068462", "reg": "AVZ2931"}, {"id": 94, "dsp": "UKED", "vin": "VXEVJYHV1R7868076", "reg": "VN74LTZ"}, {"id": 95, "dsp": "JHAL", "vin": "WF0YXXTTGYHE51186", "reg": "MJ18UOP"}, {"id": 96, "dsp": "ALMD", "vin": "W1V9106332P362529", "reg": "KO21EGU"}, {"id": 97, "dsp": "UKED", "vin": "VXEYDF6F8RG057492", "reg": "VO74LXN"}, {"id": 98, "dsp": "UKED", "vin": "VXEVJYHV9R7867824", "reg": "VN74RZX"}, {"id": 99, "dsp": "JHAL", "vin": "VF7YCTMFB12A32595", "reg": "AX65EPF"}, {"id": 100, "dsp": "ALMD", "vin": "WF0EXXTTREMG56750", "reg": "LD71ZXB"}, {"id": 101, "dsp": "ALMD", "vin": "W1V9106332P349370", "reg": "KO21OFL"}, {"id": 102, "dsp": "LIGE", "vin": "W1V9106332P348422", "reg": "KS21OLO"}]}